[{"station":"CL03","status":"active"},{"station":"CL05","status":"active"},{"station":"CL06","status":"active"},{"station":"CL07","status":"active"},{"station":"CL09","status":"active"},{"station":"CL10","status":"active"},{"station":"CL11","status":"active"},{"station":"CL12","status":"active"},{"station":"CL13","status":"warning"},{"station":"CL14","status":"active"},{"station":"CL15","status":"active"},{"station":"CL16","status":"active"},{"station":"CL17","status":"warning"},{"station":"CL18","status":"active"},{"station":"CL19","status":"active"},{"station":"CL20","status":"warning"},{"station":"CL21","status":"warning"},{"station":"LT01","status":"warning"},{"station":"LT03","status":"warning"},{"station":"LT04","status":"active"},{"station":"LT05","status":"warning"},{"station":"LT06","status":"active"},{"station":"LT07","status":"warning"},{"station":"LT08","status":"warning"},{"station":"LT09","status":"active"},{"station":"LT10","status":"active"}]
